cerillo/__about__.py
cerillo/__init__.py
cerillo/base_plate_reader.py
cerillo/rayo.py
cerillo/stratus.py
cerillo/cdcl/__init__.py
cerillo/cdcl/cdcl.py
cerillo/cdcl/experiment_builder.py
cerillo/cdcl/prefixes.py
cerillo/cdcl/start_commands.py
cerillo-0.0.3.dist-info/METADATA
cerillo-0.0.3.dist-info/WHEEL
cerillo-0.0.3.dist-info/licenses/LICENSE.txt
cerillo-0.0.3.dist-info/RECORD
