Metadata-Version: 2.4
Name: cerillo
Version: 0.0.3
Project-URL: Documentation, https://github.com/cerillo/cerillo-apps/tree/main/packages/cerillo-python#readme
Project-URL: Issues, https://github.com/cerillo/cerillo-apps/issues
Project-URL: Source, https://github.com/cerillo/cerillo-apps/tree/main/packages/cerillo-python
Author-email: cerilloderek <derek@cerillo.bio>
License-Expression: GPL-3.0-or-later
License-File: LICENSE.txt
Classifier: Development Status :: 4 - Beta
Classifier: Programming Language :: Python
Classifier: Programming Language :: Python :: 3.8
Classifier: Programming Language :: Python :: 3.9
Classifier: Programming Language :: Python :: 3.10
Classifier: Programming Language :: Python :: 3.11
Classifier: Programming Language :: Python :: 3.12
Classifier: Programming Language :: Python :: Implementation :: CPython
Classifier: Programming Language :: Python :: Implementation :: PyPy
Requires-Python: >=3.8
Requires-Dist: pyserial>=3.5
Provides-Extra: dev
Requires-Dist: pytest>=7.0; extra == 'dev'
